omotes_sdk_protocol/__init__.py
omotes_sdk_protocol/job_pb2.py
omotes_sdk_protocol/job_pb2.pyi
omotes_sdk_protocol/py.typed
omotes_sdk_protocol/workflow_pb2.py
omotes_sdk_protocol/workflow_pb2.pyi
omotes_sdk_protocol/internal/__init__.py
omotes_sdk_protocol/internal/task_pb2.py
omotes_sdk_protocol/internal/task_pb2.pyi
omotes_sdk_protocol-1.2.0.dist-info/METADATA
omotes_sdk_protocol-1.2.0.dist-info/WHEEL
omotes_sdk_protocol-1.2.0.dist-info/top_level.txt
omotes_sdk_protocol-1.2.0.dist-info/RECORD
