Metadata-Version: 2.1
Name: omotes-sdk-protocol
Version: 1.2.0
Summary: Python implementation of OMOTES SDK protocol through which jobs may be submitted and administered. Messages include checking on progress, cancelling a job and receiving status updates.
Author-email: Sebastiaan la Fleur <sebastiaan.lafleur@tno.nl>, Mark Vrijlandt <mark.vrijlandt@tno.nl>
Project-URL: homepage, https://www.nwn.nu
Project-URL: documentation, https://readthedocs.org
Project-URL: repository, https://github.com/Project-OMOTES/omotes_sdk_protocol/
Project-URL: changelog, https://github.com/Project-OMOTES/omotes_sdk_protocol/blob/main/CHANGELOG.md
Classifier: License :: OSI Approved :: GNU General Public License v3 (GPLv3)
Classifier: Programming Language :: Python :: 3
Classifier: Programming Language :: Python :: 3.11
Classifier: Operating System :: OS Independent
Classifier: Development Status :: 4 - Beta
Classifier: Intended Audience :: Developers
Classifier: Intended Audience :: Science/Research
Classifier: Intended Audience :: Information Technology
Classifier: Topic :: Scientific/Engineering
Classifier: Topic :: Scientific/Engineering :: Mathematics
Classifier: Topic :: Scientific/Engineering :: Physics
Requires-Python: >=3.9
Requires-Dist: protobuf~=5.29.1
Provides-Extra: dev
Requires-Dist: build~=1.2.2; extra == "dev"
Requires-Dist: setuptools-git-versioning<3,>=2.0; extra == "dev"
Requires-Dist: setuptools~=75.6.0; extra == "dev"
